jk_dirmonitor/DirectoryMonitor.py
jk_dirmonitor/FileEntry.py
jk_dirmonitor/__init__.py
jk_dirmonitor-0.2019.8.22.dist-info/DESCRIPTION.rst
jk_dirmonitor-0.2019.8.22.dist-info/METADATA
jk_dirmonitor-0.2019.8.22.dist-info/RECORD
jk_dirmonitor-0.2019.8.22.dist-info/WHEEL
jk_dirmonitor-0.2019.8.22.dist-info/metadata.json
jk_dirmonitor-0.2019.8.22.dist-info/top_level.txt
