Metadata-Version: 2.0
Name: jk-dirmonitor
Version: 0.2019.8.22
Summary: This python module supports checking directories for changes. (Please note that only regular files are taken into account.)
Home-page: https://github.com/jkpubsrc/python-module-jk-dirmonitor
Author: Jürgen Knauth
Author-email: pubsrc@binary-overflow.de
License: Apache 2.0
Download-URL: https://github.com/jkpubsrc/python-module-jk-dirmonitor/tarball/0.2019.8.22
Keywords: filesystem,monitoring
Platform: UNKNOWN
Classifier: Programming Language :: Python :: 3
Classifier: Development Status :: 5 - Production/Stable
Classifier: License :: OSI Approved :: Apache Software License
